odoo/addons/purchase_order_ubl/README.rst
odoo/addons/purchase_order_ubl/__init__.py
odoo/addons/purchase_order_ubl/__manifest__.py
odoo/addons/purchase_order_ubl/i18n/purchase_order_ubl.pot
odoo/addons/purchase_order_ubl/models/__init__.py
odoo/addons/purchase_order_ubl/models/purchase.py
odoo/addons/purchase_order_ubl/models/report.py
odoo/addons/purchase_order_ubl/readme/CONTRIBUTORS.rst
odoo/addons/purchase_order_ubl/readme/DESCRIPTION.rst
odoo/addons/purchase_order_ubl/static/description/icon.png
odoo/addons/purchase_order_ubl/static/description/index.html
odoo/addons/purchase_order_ubl/tests/__init__.py
odoo/addons/purchase_order_ubl/tests/test_ubl_generate.py
odoo11_addon_purchase_order_ubl-11.0.1.0.0.99.dev6.dist-info/METADATA
odoo11_addon_purchase_order_ubl-11.0.1.0.0.99.dev6.dist-info/WHEEL
odoo11_addon_purchase_order_ubl-11.0.1.0.0.99.dev6.dist-info/top_level.txt
odoo11_addon_purchase_order_ubl-11.0.1.0.0.99.dev6.dist-info/RECORD
